bashtable/__init__.py
bashtable/__main__.py
bashtable/bashtable.py
bashtable-1.0.2.dist-info/LICENSE
bashtable-1.0.2.dist-info/METADATA
bashtable-1.0.2.dist-info/WHEEL
bashtable-1.0.2.dist-info/top_level.txt
bashtable-1.0.2.dist-info/RECORD
