Metadata-Version: 2.1
Name: bashtable
Version: 1.0.2
Summary: Table package for Python
Home-page: https://github.com/rackodo/bashtable
Author: Bash Elliott
Author-email: spicethings9@gmail.com
Project-URL: Bug Tracker, https://github.com/rackodo/bashtable/issues
Classifier: Programming Language :: Python :: 3
Classifier: License :: OSI Approved :: GNU General Public License v3 (GPLv3)
Classifier: Operating System :: OS Independent
Requires-Python: >=3.6
License-File: LICENSE
